complex_jacobian/__init__.py
complex_jacobian/_core.py
complex_jacobian-0.1.0.dist-info/licenses/LICENSE
complex_jacobian-0.1.0.dist-info/METADATA
complex_jacobian-0.1.0.dist-info/WHEEL
complex_jacobian-0.1.0.dist-info/top_level.txt
complex_jacobian-0.1.0.dist-info/RECORD
