Metadata-Version: 2.4
Name: complex_jacobian
Version: 0.1.0
Summary: Complex Jacobian computation via real-valued autograd in PyTorch
Author-email: Javad Komijani <jkomijani@gmail.com>
License: MIT License
Project-URL: Homepage, https://github.com/jkomijani/complex_jacobian
Requires-Python: >=3.8
License-File: LICENSE
Requires-Dist: torch
Dynamic: license-file
